feed_sinai/__init__.py
feed_sinai/feed_sinai.py
feed_sinai/py.typed
feed_sinai/sinai_json_importer.py
feed_sinai/sinai_types.py
feed_sinai/solr_record.py
feed_ursus/__init__.py
feed_ursus/date_parser.py
feed_ursus/feed_ursus.py
feed_ursus/importer.py
feed_ursus/py.typed
feed_ursus/year_parser.py
feed_ursus/mapper/__init__.py
feed_ursus/mapper/dlp.py
feed_ursus/mapper/sinai.py
feed_ursus/mapper/fields/iiif_text_direction.yml
feed_ursus/mapper/fields/iiif_viewing_hint.yml
feed_ursus/mapper/fields/language.yml
feed_ursus/mapper/fields/license.yml
feed_ursus/mapper/fields/resource_type.yml
feed_ursus/mapper/fields/rights_statement.yml
feed_ursus-1.5.0.dist-info/METADATA
feed_ursus-1.5.0.dist-info/WHEEL
feed_ursus-1.5.0.dist-info/entry_points.txt
feed_ursus-1.5.0.dist-info/licenses/LICENSE
feed_ursus-1.5.0.dist-info/RECORD
