Metadata-Version: 2.4
Name: feed-ursus
Version: 1.5.0
Summary: Command line tool to load CSV content into a Solr index for the UCLA Digital Library's frontend, Ursus (https://digital.library.ucla.edu/)
Author-email: Andy Wallace <andrewwallace@library.ucla.edu>
License-File: LICENSE
Requires-Python: ~=3.10
Requires-Dist: click>=8.1.3
Requires-Dist: edtf>=5.0.0
Requires-Dist: httpx>=0.28.1
Requires-Dist: pydantic<3,>=2.11.7
Requires-Dist: pysolr>=3.8
Requires-Dist: python-dateutil>=2.8.2
Requires-Dist: pyyaml>=6.0.1
Requires-Dist: requests>=2.32.2
Requires-Dist: rich>=13.4.1
Requires-Dist: setuptools>=74
